[
    {
        "name": "Male voice",
        "message": "It's about time......"
    },
    {
        "name": "Female voice",
        "message": "Yes, her water's about to break any minute now."
    },
    {
        "name": "Male voice",
        "message": "女、お前怯えているのか？"
    },
    {
        "name": "Male voice",
        "message": "It's too late to have such human-like feelings now."
    },
    {
        "name": "Male voice",
        "message": "You're getting exactly what you deserve for losing your self-control and indulging in beastly pleasure."
    },
    {
        "name": "Male voice",
        "message": "It's no use regretting it now, is it？"
    },
    {
        "name": "Male voice",
        "message": "Now, you must pay the price for that pleasure."
    },
    {
        "message": "　　　　　　You have to endure pain even worse than death."
    },
    {
        "name": "Male voice",
        "message": "Are you scared？"
    },
    {
        "message": "　　　　　　You better be scared, as much as you can."
    },
    {
        "name": "Male voice",
        "message": "Feeling like that is only for now."
    },
    {
        "name": "Male voice",
        "message": "Hold her legs down, spread them apart."
    },
    {
        "name": "Female voice",
        "message": "Yes......"
    },
    {
        "name": "Male voice",
        "message": "It's almost time........."
    },
    {
        "name": "Male voice",
        "message": "It's about to be born soon."
    },
    {
        "name": "Female voice",
        "message": "The birth canal is open, I think it'll be fine like this......"
    },
    {
        "name": "Male voice",
        "message": "Of course-it's a mouth that's swallowed all sorts of filthy things."
    },
    {
        "message": "　　　　　　Opening that mouth wide without a hint of shame."
    },
    {
        "name": "Male voice",
        "message": "Getting your belly cut open would probably be a lot easier, though......"
    },
    {
        "message": "　　　　　　But it's all your own lewd body's fault."
    },
    {
        "name": "Male voice",
        "message": "If you want to hate someone, hate yourself！"
    },
    {
        "name": "Female voice",
        "message": "It's about time."
    },
    {
        "name": "Male voice",
        "message": "Alright, rip her clothes."
    },
    {
        "name": "Chained woman",
        "message": "Nngh... ngh！"
    },
    {
        "name": "Male voice",
        "message": "Does it hurt？"
    },
    {
        "name": "Male voice",
        "message": "Yeah, I figured."
    },
    {
        "message": "　　　　　　Nobody's gonna help you."
    },
    {
        "name": "Male voice",
        "message": "Committing a sin so great even God turns His back on you, huh."
    },
    {
        "name": "Male voice",
        "message": "Struggle all you want."
    },
    {
        "message": "　　　　　　That's the karma you took on."
    },
    {
        "name": "Female voice",
        "message": "It's started！"
    },
    {
        "name": "Chained woman",
        "message": "Nn..."
    },
    {
        "name": "Male voice",
        "message": "Not yet..."
    },
    {
        "name": "Chained woman",
        "message": "Nngh......"
    },
    {
        "name": "Female voice",
        "message": "The head's coming out a little more."
    },
    {
        "name": "Male voice",
        "message": "Not yet! I won’t let you die yet!"
    },
    {
        "name": "Male voice",
        "message": "Accept that suffering."
    },
    {
        "message": "　　　　　　It's time to pay for all the fun you've had."
    },
    {
        "name": "Female voice",
        "message": "The blood... the bleeding's too much..."
    },
    {
        "name": "Male voice",
        "message": "Spread your legs wider！"
    },
    {
        "message": "　　　　　　I don't care what happens to this woman."
    },
    {
        "name": "Female voice",
        "message": "But like this... I won't last until the end."
    },
    {
        "name": "Male voice",
        "message": "Doesn't matter, if it comes to that I'll drag it out myself."
    },
    {
        "name": "Chained woman",
        "message": "Nngh！"
    },
    {
        "name": "Male voice",
        "message": "Come on... show yourself... you filthy beast！"
    },
    {
        "name": "Male voice",
        "message": "You bastard... I won't let you die that easily！"
    },
    {
        "name": "Chained woman",
        "message": "Nngh......kuh......"
    },
    {
        "name": "Female voice",
        "message": "Ah......just a little more......"
    },
    {
        "name": "Male voice",
        "message": "Yeah... that's it. Keep it up."
    },
    {
        "name": "Male voice",
        "message": "From that mouth that swallowed abominable filth, a lump filled with disgust, born of your sins, is poking its face out."
    },
    {
        "name": "Male voice",
        "message": "Come on, what's wrong！"
    },
    {
        "message": "　　　　　　Do your damn duty."
    },
    {
        "name": "Chained woman",
        "message": "Nngh... nngh！"
    },
    {
        "name": "Chained woman",
        "message": "Uuun...nnn-aaah！"
    },
    {
        "name": "Female voice",
        "message": "I...I'm dead..."
    },
    {
        "name": "Female voice",
        "message": "A woman..."
    },
    {
        "name": "Male voice",
        "message": "Don't worry about it！"
    },
    {
        "name": "Male voice",
        "message": "What happened to the baby...！"
    },
    {
        "name": "Male voice",
        "message": "Again......"
    },
    {
        "name": "Male voice",
        "message": "Another failure, huh......"
    },
    {
        "name": "Male voice",
        "message": "Why is it, what the hell is wrong with it！"
    },
    {
        "name": "Female voice",
        "message": "What will you do？"
    },
    {
        "name": "Male voice",
        "message": "It's decided！"
    },
    {
        "name": "Male voice",
        "message": "Not interested in failures..."
    },
    {
        "name": "Female voice",
        "message": "Well then..."
    },
    {
        "name": "Male voice",
        "message": "No choice but to finish it off."
    },
    {
        "name": "Male voice",
        "message": "You ugly monster."
    },
    {
        "name": "Male voice",
        "message": "Are you actually feeling scared now？"
    },
    {
        "name": "Male voice",
        "message": "Look at it squirm and try to run away."
    },
    {
        "message": "　　　　　　Impressive. No wonder, with how strong the beast blood runs in it."
    },
    {
        "name": "Female voice",
        "message": "H-hurry... if you don't do it soon..."
    },
    {
        "name": "Male voice",
        "message": "I know already."
    },
    {
        "name": "Female voice",
        "message": "It's... it's looking over here！"
    },
    {
        "name": "Male voice",
        "message": "Do you hate me？"
    },
    {
        "message": "　　　　　　Do you have feelings too?"
    },
    {
        "name": "Male voice",
        "message": "Even though I'm the one who brought you into this world."
    },
    {
        "name": "Male voice",
        "message": "Sorry, but... you don't even have the right to live！"
    }
]