[
  {
    "message": "さすがに陽が落ちた後に来ると、寒気にも似た恐怖感を感じる。"
  },
  {
    "message": "何百という修道女が焼け死んだ忌まわしい場所だ、夜にひとりで来るには相応しくない。"
  },
  {
    "message": "ましてや、昼間あんな事があった後では‥‥‥‥‥"
  },
  {
    "message": "私が怖じ気付いたとしても、誰がそれを責められると言うのだ？"
  },
  {
    "message": "燃え落ちた修道院の跡だ。"
  },
  {
    "message": "百年以上も前の火災以来、全ての人間に忘れ去られてしまったかのように放置されている。"
  },
  {
    "message": "ミスカトニック修道院の跡地だ。"
  },
  {
    "message": "あたりには黒く煤けた石や、炭になった柱があり、火災のすさまじさを物語っている。"
  },
  {
    "message": "修道院の跡地だ。"
  },
  {
    "message": "私の夢の中に出てきた修道院とは、ここの事なのだろうか？"
  },
  {
    "message": "雪の中を歩いていたふたりの彼方に見えた建物は、かなり大がかりな石造りの建物だった。"
  },
  {
    "message": "こう酷い有様では、ふたつの建物が同一の物だと確証を持てない。"
  },
  {
    "message": "確か、夢の中の『マリア』という修道院長は『ミスカトニック修道院』と言っていた。"
  },
  {
    "name": "コーデリア",
    "message": "どうしたの、さっきから考え込んでしまって。"
  },
  {
    "message": "　　　　　　　　何か問題でもあるの？"
  },
  {
    "name": "ジョナサン",
    "message": "ここが私の夢に出てきた修道院なのだろうかと考えて　　　　　　　　いたんだ。"
  },
  {
    "name": "コーデリア",
    "message": "夢？"
  },
  {
    "message": "　　　　　　　　また修道院の夢を見たの。"
  },
  {
    "name": "ジョナサン",
    "message": "おかしな話だが、アーカムに来て以来毎晩のように夢　　　　　　　　を見続けているんだ。"
  },
  {
    "name": "コーデリア",
    "message": "この修道院跡が、ジョナサンの夢の中に出てきたのと　　　　　　　　同じだって言うのね。"
  },
  {
    "name": "ジョナサン",
    "message": "確証はないが‥‥‥‥"
  },
  {
    "message": "　　　　　　　　どうもそうなんじゃないかという気がする。"
  },
  {
    "message": "普段ならこのような豊かな緑を目にすると心休まる気がするものだが、ここでは、木々の間から人ならぬ何物かがこちらの様子を伺っているのではないかという恐怖感が先立ってそれどころではない。"
  },
  {
    "message": "１００年以上の樹齢を数える老木が密生している。"
  },
  {
    "message": "修道院で起こった火災の何を逃れて、当時からそこにあったのだろう。"
  },
  {
    "message": "片田舎のわりには緑が少ないアーカムの中心部とは違い、人間が容易に入れ込めないほどに濃い緑だ。"
  },
  {
    "message": "石が整然と並んだ床が、修道院がまだ存在していた頃の面影をわずかに忍ばせている。"
  },
  {
    "message": "あたりには火災の跡を物語る、炭になった木片や、割れた石材の破片などがいたる所に散乱している。"
  },
  {
    "message": "それにしても、修道院の建物を構成していたにしては、異様なほど石や柱の数が少ない。"
  },
  {
    "message": "それらの大半は、新しい建物を造るための材料として、何物かに持ち去られてしまったのだろうが、それにしてもこれでは更地同然だ。"
  },
  {
    "name": "ジョナサン",
    "message": "修道院の廃墟に地下室があるなんて。"
  },
  {
    "message": "　　　　　　　　ちょっと普通ではないように思えるな。"
  },
  {
    "name": "ジョナサン",
    "message": "ちょっと待って下さい、あれは何でしょう。"
  },
  {
    "message": "一見すると瓦礫の山のようだが、崩れた石の下に何かがあるようだ。"
  },
  {
    "message": "よく見ると‥‥‥‥‥"
  },
  {
    "name": "コーデリア",
    "message": "何かあるみたい。"
  },
  {
    "message": "　　　　　　　　あそこだけ異様に石が積んであるわ。"
  },
  {
    "message": "誰かが故意にやった物だとすると、他人の目に触れさせたくないような何かが隠してあるのかも‥‥‥‥‥"
  },
  {
    "name": "コーデリア",
    "message": "よく見て、あれ、階段じゃ‥‥‥‥"
  },
  {
    "message": "瓦礫の下には、地下に通じる穴がぽっかりと口を開けている。"
  },
  {
    "message": "よく見ると、階段のような物があるようだ。"
  },
  {
    "name": "ジョナサン",
    "message": "この邪魔な石をどければ、地下に降りられるかも。"
  },
  {
    "message": "　　　　　　　　この下に地下室があるんですよ。"
  },
  {
    "name": "ガードナー",
    "message": "修道院に地下室か、考えられない事もない。"
  },
  {
    "message": "　　　　　　　　うまくすると火災を免れているかもしれないな。"
  },
  {
    "name": "ジョナサン",
    "message": "降りてみましょうか？"
  },
  {
    "name": "コーデリア",
    "message": "危ないんじゃないかしら。"
  },
  {
    "message": "　　　　　　　　いつ天井が崩れてくるかもしれないわ。"
  },
  {
    "message": "少しでも往時の面影を残していれば、大した観光の名所となっただろうに、これでは誰かに聞かなければ何があったのか解るはずもない。"
  },
  {
    "message": "ほんのわずかに残った建物の一部は、おそらく礼拝堂などのある大きな建物に並んで建てられた、小さな別棟の名残りなのだろう。"
  },
  {
    "message": "入り口の跡と思われる石で縁取られたアーチ様の物の規模から考えると食料やその他の必需品を蓄えておくための物置のような建物ではなかったかと推測される。"
  },
  {
    "message": "修道院のもっとも大切な部分は跡形もなくなってしまったというのに、どうでもいいような別棟がその面影を残す事になるとは、なんと皮肉な話なのだろう。"
  },
  {
    "name": "コーデリア",
    "message": "ジョナサンとこの修道院は何か関係があるのよ。"
  },
  {
    "message": "　　　　　　　　そうじゃなければ、そんなおかしな夢を見る訳がない　　　　　　　　じゃないの。"
  },
  {
    "name": "コーデリア",
    "message": "ジョナサンの見た夢って、どんなだったの？"
  },
  {
    "message": "　　　　　　　　修道院の夢って事は女の人ばかりだったんでしょう。"
  },
  {
    "name": "ジョナサン",
    "message": "まあそうだが‥‥‥‥"
  },
  {
    "message": "　　　　　　　　別にいやらしい夢を見ていた訳ではないよ。"
  },
  {
    "name": "ジョナサン",
    "message": "なんだか妙に臨場感があって、まるで自分が修道院の　　　　　　　　中に入り込んでしまったようだった。"
  },
  {
    "name": "コーデリア",
    "message": "どんな事を見たの？"
  },
  {
    "name": "ジョナサン",
    "message": "修道院にふたりの女性がやって来るところだった。"
  },
  {
    "message": "　　　　　　　　ひとりはまだ十代のはじめ頃の年齢だった。"
  },
  {
    "name": "コーデリア",
    "message": "そんな子供の修道女もいたのね。"
  },
  {
    "message": "　　　　　　　　まだ世の中の事を何も知らないうちに、外と隔絶され　　　　　　　　た修道院に来るなんて可哀相。"
  },
  {
    "name": "ジョナサン",
    "message": "しかも新しく修道院にやって来た女性は、この院内で　　　　　　　　背信的な何かが行われていると確信していたんだ。"
  },
  {
    "name": "コーデリア",
    "message": "それを調べるために修道院にやって来たのね？"
  },
  {
    "name": "ジョナサン",
    "message": "そう言っていた。"
  },
  {
    "message": "　　　　　　　　さっぱり訳が解らない話だろう？"
  },
  {
    "name": "トマス",
    "message": "夜になったら俺の部屋に来いよ。"
  },
  {
    "message": "　　　　　　今晩はお前が来るまで待っていてやるからよ。"
  },
  {
    "name": "ジョナサン",
    "message": "今朝言っていた『いいところ』ってのは何処なんだ。　　　　　　　　あんな夜更けでなければ行けない所なのか？"
  },
  {
    "message": "ナイと会っていた事をごまかすための体のいい口実なんじゃないか？"
  },
  {
    "message": "第一、トマスはアーカムにそんな所があるとどうして知ったんだ。"
  },
  {
    "name": "トマス",
    "message": "今晩連れていってやるって言ってるだろうが。"
  },
  {
    "message": "　　　　　　そんなに焦るんじゃねえよ。"
  },
  {
    "name": "ジョナサン",
    "message": "この村の中に君が好みそうな場所なんてあるのか？"
  },
  {
    "name": "トマス",
    "message": "くどいぜ、夜になれば解るって言ってるじゃねえか。"
  },
  {
    "message": "　　　　　　お前だって一回行けばやみつきになるぜ。"
  },
  {
    "message": "この男が言うとひどくいかがわしい所のような気がする。"
  },
  {
    "message": "まさか、昔よくあった阿片窟のような場所じゃないだろうな‥‥‥"
  },
  {
    "name": "トマス",
    "message": "そんなに考えこむなって。"
  },
  {
    "message": "　　　　　　行ってみりゃ解る事じゃねえか。"
  },
  {
    "name": "ガードナー",
    "message": "はて、こんな所で何を探したものやら‥‥‥‥"
  },
  {
    "message": "　　　　　　　　見渡す限り焼け跡ばかりじゃないか。"
  },
  {
    "name": "ガードナー",
    "message": "はて、こんな所で何を探したものやら‥‥‥‥"
  },
  {
    "message": "　　　　　　　　見渡す限り焼け跡ばかりじゃないか。"
  },
  {
    "name": "ジョナサン",
    "message": "しかし、私がアーカムに来て以来見続けている夢と、　　　　　　　　この修道院は無関係ではないような気がするんです。"
  },
  {
    "name": "ガードナー",
    "message": "確かに、それまで見たこともない修道院の夢を見続け　　　　　　　　ると言うのは妙な話だな。"
  },
  {
    "name": "ガードナー",
    "message": "しかも、都合がいい事に、村には修道院があった。"
  },
  {
    "message": "　　　　　　　　何らかの関連があると考えても不思議ではないがね。"
  },
  {
    "name": "ジョナサン",
    "message": "何か不審な事でもあるんですか？"
  },
  {
    "name": "ガードナー",
    "message": "実は君は、自分でも忘れているが以前にアーカムに来　　　　　　　　た事があるとは考えられんかね。"
  },
  {
    "name": "ガードナー",
    "message": "無意識のうちにアーカムの事を思い出し、それが夢に　　　　　　　　なっているのではないかな。"
  },
  {
    "name": "ジョナサン",
    "message": "そんな事はあり得ませんよ。"
  },
  {
    "message": "　　　　　　　　わが家ではアーカムの名前を口に出す事さえ禁忌だっ　　　　　　　　たのですから。"
  },
  {
    "name": "ガードナー",
    "message": "そうか‥‥‥‥"
  },
  {
    "message": "完全に炭化してしまっている木材は、私がほんの少し手を触れただけでもボロボロに崩れてしまう。"
  },
  {
    "message": "どんなにひどい火災がこの修道院を襲ったのだろうか。"
  },
  {
    "message": "　　　地図　　　"
  },
  {
    "message": "　　中に入る　　"
  },
  {
    "message": "　　　地図　　　"
  }
]